gdbyvgt/__init__.py
gdbyvgt/gradient.py
gdbyvgt-0.0.6.dist-info/LICENSE
gdbyvgt-0.0.6.dist-info/METADATA
gdbyvgt-0.0.6.dist-info/WHEEL
gdbyvgt-0.0.6.dist-info/top_level.txt
gdbyvgt-0.0.6.dist-info/RECORD
