Metadata-Version: 2.1
Name: gdbyvgt
Version: 0.0.6
Summary: Gradient Descent implementation by Vu Gia Tue
Home-page: https://github.com/AndrewVu-VuGiaTue/gdbyvgt
Author: Gia Tue Vu (AndrewVu)
Author-email: vgt2800@gmail.com
License: MIT
Platform: UNKNOWN
Classifier: Development Status :: 5 - Production/Stable
Classifier: Intended Audience :: Education
Classifier: Operating System :: OS Independent
Classifier: License :: OSI Approved :: MIT License
Classifier: Programming Language :: Python :: 3
Requires-Python: >=3.6
Requires-Dist: numpy
